mydload/__init__.py
mydload/mydload.py
mydload-0.0.7.dist-info/LICENSE
mydload-0.0.7.dist-info/METADATA
mydload-0.0.7.dist-info/WHEEL
mydload-0.0.7.dist-info/top_level.txt
mydload-0.0.7.dist-info/RECORD
